LICENSE
MANIFEST.in
README.rst
setup.py
anonsurvey/__init__.py
anonsurvey/admin.py
anonsurvey/models.py
anonsurvey/tests.py
anonsurvey/urls.py
anonsurvey/utils.py
anonsurvey/validators.py
anonsurvey/views.py
anonsurvey/templates/anonsurvey/survey.html
anonsurvey/templates/anonsurvey/survey_base.html
anonsurvey/templates/anonsurvey/survey_form.html
anonsurvey/templates/anonsurvey/survey_thanks.html
anonsurvey/templates/anonsurvey/surveys.html
anonsurvey/templatetags/__init__.py
anonsurvey/templatetags/anonsurvey_extras.py
django_anonsurvey.egg-info/PKG-INFO
django_anonsurvey.egg-info/SOURCES.txt
django_anonsurvey.egg-info/dependency_links.txt
django_anonsurvey.egg-info/requires.txt
django_anonsurvey.egg-info/top_level.txt